{
    "header": {
        "title": {
            "default": "Polyas Verifier",
            "value": {
                "DE": "Polyas-Verifier"
            }
        },
        "election": {
            "default": "Election Title: ",
            "value": {
                "DE": "Titel der Wahl: "
            }
        },
        "language": {
            "default": "Language selection: ",
            "value": {
                "DE": "Sprachauswahl: "
            }
        }
    },
    "footer": {
        "acknowledgement": {
            "default": "by KASTEL Security Research Labs at Karlsruhe Institute of Technology (KIT).",
            "value": {
                "DE": "von den KASTEL-Sicherheitsforschungslaboren am Karlsruher Institut für Technologie (KIT)."
            }
        }
    },
    "login": {
        "loginReq": {
            "default": "Enter one-time password",
            "value": {
                "DE": "Einmalpasswort eingeben"
            }
        },
        "loginButton": {
            "default": "login",
            "value": {"DE": "anmelden"}
        },
        "voterId": {
            "default": "Voter ID: ",
            "value": {"DE": "Wähler:innen-ID: "}
        }
    },
    "verified": {
        "verified": {
            "default": "Your ballot has been successfully verified.",
            "value": {
                "DE": "Ihr Stimmzettel wurde erfolgreich verifiziert."
            }
        },
        "explanation": {
            "default": "Please note that the following is an image of your ballot in the ballot box. You can no longer change your submitted ballot. You can edit the image to hide your vote, but doing so will not impact your submitted ballot.",
            "value": {
                "DE": "Bitte beachten Sie: Im Folgenden sehen Sie ein Abbild Ihres Stimmzettels in der Wahlurne. Sie können Ihren Stimmzettel nicht mehr verändern. Allerdings können Sie das folgende Abbild verändern, um Ihre Stimmabgabe zu verbergen. Dies wird jedoch Ihren abgegebenen Stimmzettel in der Wahlurne nicht beeinflussen."
            }
        },
        "verifiedFor": {
            "default": "Verified for: ",
            "value": {
                "DE": "Verifiziert für: "
            }
        },
        "electionId": {
            "default": "Election: ",
            "value": {
                "DE": "Wahl: "
            }
        },
        "voterId": {
            "default": "Voter: ",
            "value": {
                "DE": "Wähler: "
            }
        },
        "label": {
            "default": "Ballot sheets: ",
            "value": {
                "DE": "Stimmzettel: "
            }
        },
        "downloadText": {
            "default": "You can download a receipt that contains a confirmation of the election server that your ballot is included in the ballot box. After the election, you can use this receipt with a universal verification tool to confirm that your ballot is correctly included in the tally.",
            "value": {
                "DE": "Sie können eine Bestätigung vom Wahlserver herunterladen, dass Ihr Stimmzettel in der Wahlurne enthalten ist. Nach der Wahl können Sie unter Verwendung eines universellen Verifizierungstools mit dieser Bestätigung überprüfen, dass ihr Stimmzettel auch korrekt in der Auszählung berücksichtigt wurde."
            }
        },
        "download": {
            "default": "Download receipt of the vote casting.",
            "value": {
                "DE": "Bestätigung der Stimmabgabe herunterladen."
            }
        }

    },
    "ballot": {
        "invalidOption": {
            "default": "invalid",
            "value": {
                "DE": "ungültig"
            }
        },
        "abstainOption": {
            "default": "Your ballot is explicitly marked as abstention",
            "value": {
                "DE": "Stimmzettel als Enthaltung markiert"
            }
        },
        "listVote": {
            "default": "Vote for candidate list",
            "value": {
                "DE": "Stimme für Kandidierendenliste"
            }
        },
        "defaultColumn": {
            "contentType": "TEXT",
            "value": {
                "default": "unknown",
                "value": {"DE": "unbekannt"}
            }
        }
    },
    "error": {
        "params": {
            "default": "The URL you have entered is invalid. Please enter this page by scanning the QR code offered by your voting application, without modifying this code or the URL.",
            "value": {
                "DE": "Die eingegebene URL ist ungültig. Bitte rufen Sie diese Seite durch Scannen des QR-Codes der Wahlanwendung auf, ohne diesen Code oder die URL zu modifizieren."
            }
        },
        "rejected": {
            "default": "Your ballot could not be verified.",
            "value": {
                "DE": "Ihr Stimmzettel konnte nicht verifiziert werden."
            }
        },
        "connection": {
            "default": "A connection issue occured.",
            "value": {
                "DE": "Ein Verbindungsfehler ist aufgetreten."
            }
        },
        "extern": {
            "default": "The cryptographic exchange was rejected by the election server. Have you maybe entered the one-time password incorrectly or did the time limit for the verification run out?",
            "value": {
                "DE": "Der kryptographische Austausch wurde vom Wahlserver zurückgewiesen. Haben Sie vielleicht das Einmalpasswort falsch eingegeben oder wurde das Zeitlimit der Verifizierung erreicht?"
            }
        },
        "sdpp": {
            "default": "The second device parameters returned by the election server do not match the pre-configured fingerprint. This could be caused by a third party attack. Please contact the election administration.",
            "value": {
                "DE": "Die vom Wahlserver erhaltenen Zweitgerät-Parameter passen nicht zum voreingestellen Fingerabdruck. Dies könnte durch einen Angriff einer dritten Partei verursacht sein. Bitte setzten Sie sich mit der Wahlleitung in Verbindung."
            }
        },
        "ack": {
            "default": "The ballot acknowledgement sent by the election server is invalid. This could be caused by a third party attack.",
            "value": {
                "DE": "Die Bestätigung des Stimmzettels durch den Wahlserver ist ungültig. Dies könnte durch einen Angriff einer dritten Partei verursacht sein."
            }
        },
        "decrypt": {
            "default": "A parameter passed with the URL was invalid. This could be caused by a third party attack.",
            "value": {
                "DE": "Ein mit der URL übermittelter Parameter ist ungültig. Dies könnte durch einen Angriff einer dritten Partei verursacht sein."
            }
        },
        "format": {
            "default": "The format of a message passed by the election server is invalid.",
            "value": {
                "DE": "Eine Nachricht vom Wahlserver hat ein ungültiges Format."
            }
        },
        "zkp_inv": {
            "default": "The zero-knowledge proof provided by the election server is invalid. This could be caused by a third party attack.",
            "value": {
                "DE": "Der Zero-Knowledge Beweis des Wahlservers ist ungültig. Dies könnte auf durch einen Angriff einer dritten Partei verursacht sein."
            }
        },
        "other": {
            "default": "An error occured. This is likely the result of a programming mistake in the verifier, and not a mistake of the election server or an attack by a third party.",
            "value": {
                "DE": "Ein Fehler ist aufgetreten. Dieser ist wahrscheinlich durch einen Programmierfehler im Verifizierer verursacht worden und wurde nicht durch einen Fehler des Wahlservers oder einen Angriff einer dritten Partei ausgelöst."
            }
        },
        "decode": {
            "default": "The decoded ballot does not fit the format required by the ballot sheet.",
            "value": {
                "DE": "Der dekodierte Stimmzettel passt nicht zum im Stimmzettelbogen vorgegebenen Format"
            }
        },
        "reset": {
            "default": "Retry login",
            "value": {
                "DE": "Anmelden wiederholen"
            }
        }
    }
}
